Workbook

Sheet Dashboard

Sheet Daily Sales
A1: Date | B1: Customer Name | C1: Product Name | D1: Quantity Sold | E1: Selling Price | F1: Payment Method | G1: Full Cash | H1: Partly Payment | I1: Total Credit | J1: Total | K1: Profit
A2: 45608 | B2: MUMBEJA | C2: NAMANVE | D2: 5 | E2: 140000 | F2: Full Cash | G2: =IF(F2="Full Cash", D2*E2, "") -> 700000 | I2: =IF(F2="Full Credit",D2*E2,IF(F2="Partly Payment",(D2*E2)-H2,"")) | J2: =IF(F2="Full Cash", G2, IF(F2="Full Credit", I2, IF(F2="Partly Payment", H2+I2, ""))) -> 700000 | K2: =IFERROR((E2 - VLOOKUP(C2, 'Stock Entry'!B:E, 4, FALSE)) * D2, "") -> 190000
A3: 45638 | B3: KAMWEKAMWE | C3: MUYINDI | D3: 10 | E3: 140000 | F3: Full Cash | G3: =IF(F3="Full Cash", D3*E3, "") -> 1400000 | I3: =IF(F3="Full Credit",D3*E3,IF(F3="Partly Payment",(D3*E3)-H3,"")) | J3: =IF(F3="Full Cash", G3, IF(F3="Full Credit", I3, IF(F3="Partly Payment", H3+I3, ""))) -> 1400000 | K3: =IFERROR((E3 - VLOOKUP(C3, 'Stock Entry'!B:E, 4, FALSE)) * D3, "") -> 280000
G4: =IF(F4="Full Cash", D4*E4, "") | I4: =IF(F4="Full Credit",D4*E4,IF(F4="Partly Payment",(D4*E4)-H4,"")) | J4: =IF(F4="Full Cash", G4, IF(F4="Full Credit", I4, IF(F4="Partly Payment", H4+I4, ""))) | K4: =IFERROR((E4 - VLOOKUP(C4, 'Stock Entry'!B:E, 4, FALSE)) * D4, "")
G5: =IF(F5="Full Cash", D5*E5, "") | I5: =IF(F5="Full Credit",D5*E5,IF(F5="Partly Payment",(D5*E5)-H5,"")) | J5: =IF(F5="Full Cash", G5, IF(F5="Full Credit", I5, IF(F5="Partly Payment", H5+I5, ""))) | K5: =IFERROR((E5 - VLOOKUP(C5, 'Stock Entry'!B:E, 4, FALSE)) * D5, "")
G6: =IF(F6="Full Cash", D6*E6, "") | I6: =IF(F6="Full Credit",D6*E6,IF(F6="Partly Payment",(D6*E6)-H6,"")) | J6: =IF(F6="Full Cash", G6, IF(F6="Full Credit", I6, IF(F6="Partly Payment", H6+I6, ""))) | K6: =IFERROR((E6 - VLOOKUP(C6, 'Stock Entry'!B:E, 4, FALSE)) * D6, "")
G7: =IF(F7="Full Cash", D7*E7, "") | I7: =IF(F7="Full Credit",D7*E7,IF(F7="Partly Payment",(D7*E7)-H7,"")) | J7: =IF(F7="Full Cash", G7, IF(F7="Full Credit", I7, IF(F7="Partly Payment", H7+I7, ""))) | K7: =IFERROR((E7 - VLOOKUP(C7, 'Stock Entry'!B:E, 4, FALSE)) * D7, "")
G8: =IF(F8="Full Cash", D8*E8, "") | I8: =IF(F8="Full Credit",D8*E8,IF(F8="Partly Payment",(D8*E8)-H8,"")) | J8: =IF(F8="Full Cash", G8, IF(F8="Full Credit", I8, IF(F8="Partly Payment", H8+I8, ""))) | K8: =IFERROR((E8 - VLOOKUP(C8, 'Stock Entry'!B:E, 4, FALSE)) * D8, "")
G9: =IF(F9="Full Cash", D9*E9, "") | I9: =IF(F9="Full Credit",D9*E9,IF(F9="Partly Payment",(D9*E9)-H9,"")) | J9: =IF(F9="Full Cash", G9, IF(F9="Full Credit", I9, IF(F9="Partly Payment", H9+I9, ""))) | K9: =IFERROR((E9 - VLOOKUP(C9, 'Stock Entry'!B:E, 4, FALSE)) * D9, "")
G10: =IF(F10="Full Cash", D10*E10, "") | I10: =IF(F10="Full Credit",D10*E10,IF(F10="Partly Payment",(D10*E10)-H10,"")) | J10: =IF(F10="Full Cash", G10, IF(F10="Full Credit", I10, IF(F10="Partly Payment", H10+I10, ""))) | K10: =IFERROR((E10 - VLOOKUP(C10, 'Stock Entry'!B:E, 4, FALSE)) * D10, "")
G11: =IF(F11="Full Cash", D11*E11, "") | I11: =IF(F11="Full Credit",D11*E11,IF(F11="Partly Payment",(D11*E11)-H11,"")) | J11: =IF(F11="Full Cash", G11, IF(F11="Full Credit", I11, IF(F11="Partly Payment", H11+I11, ""))) | K11: =IFERROR((E11 - VLOOKUP(C11, 'Stock Entry'!B:E, 4, FALSE)) * D11, "")
G12: =IF(F12="Full Cash", D12*E12, "") | I12: =IF(F12="Full Credit",D12*E12,IF(F12="Partly Payment",(D12*E12)-H12,"")) | J12: =IF(F12="Full Cash", G12, IF(F12="Full Credit", I12, IF(F12="Partly Payment", H12+I12, ""))) | K12: =IFERROR((E12 - VLOOKUP(C12, 'Stock Entry'!B:E, 4, FALSE)) * D12, "")
G13: =IF(F13="Full Cash", D13*E13, "") | I13: =IF(F13="Full Credit",D13*E13,IF(F13="Partly Payment",(D13*E13)-H13,"")) | J13: =IF(F13="Full Cash", G13, IF(F13="Full Credit", I13, IF(F13="Partly Payment", H13+I13, ""))) | K13: =IFERROR((E13 - VLOOKUP(C13, 'Stock Entry'!B:E, 4, FALSE)) * D13, "")
G14: =IF(F14="Full Cash", D14*E14, "") | I14: =IF(F14="Full Credit",D14*E14,IF(F14="Partly Payment",(D14*E14)-H14,"")) | J14: =IF(F14="Full Cash", G14, IF(F14="Full Credit", I14, IF(F14="Partly Payment", H14+I14, ""))) | K14: =IFERROR((E14 - VLOOKUP(C14, 'Stock Entry'!B:E, 4, FALSE)) * D14, "")
G15: =IF(F15="Full Cash", D15*E15, "") | I15: =IF(F15="Full Credit",D15*E15,IF(F15="Partly Payment",(D15*E15)-H15,"")) | J15: =IF(F15="Full Cash", G15, IF(F15="Full Credit", I15, IF(F15="Partly Payment", H15+I15, ""))) | K15: =IFERROR((E15 - VLOOKUP(C15, 'Stock Entry'!B:E, 4, FALSE)) * D15, "")
... G1242: =IF(F1242="Full Cash", D1242*E1242, "") | I1242: =IF(F1242="Full Credit",D1242*E1242,IF(F1242="Partly Payment",(D1242*E1242)-H1242,"")) | J1242: =IF(F1242="Full Cash", G1242, IF(F1242="Full Credit", I1242, IF(F1242="Partly Payment", H1242+I1242, ""))) | K1242: =IFERROR((E1242 - VLOOKUP(C1242, 'Stock Entry'!B:E, 4, FALSE)) * D1242, "")
I1243: =IF(F1243="Full Credit",D1243*E1243,IF(F1243="Partly Payment",(D1243*E1243)-H1243,"")) | J1243: =IF(F1243="Full Cash", G1243, IF(F1243="Full Credit", I1243, IF(F1243="Partly Payment", H1243+I1243, ""))) | K1243: =IFERROR((E1243 - VLOOKUP(C1243, 'Stock Entry'!B:E, 4, FALSE)) * D1243, "")
I1244: =IF(F1244="Full Credit",D1244*E1244,IF(F1244="Partly Payment",(D1244*E1244)-H1244,"")) | J1244: =IF(F1244="Full Cash", G1244, IF(F1244="Full Credit", I1244, IF(F1244="Partly Payment", H1244+I1244, ""))) | K1244: =IFERROR((E1244 - VLOOKUP(C1244, 'Stock Entry'!B:E, 4, FALSE)) * D1244, "")
I1245: =IF(F1245="Full Credit",D1245*E1245,IF(F1245="Partly Payment",(D1245*E1245)-H1245,"")) | J1245: =IF(F1245="Full Cash", G1245, IF(F1245="Full Credit", I1245, IF(F1245="Partly Payment", H1245+I1245, ""))) | K1245: =IFERROR((E1245 - VLOOKUP(C1245, 'Stock Entry'!B:E, 4, FALSE)) * D1245, "")
I1246: =IF(F1246="Full Credit",D1246*E1246,IF(F1246="Partly Payment",(D1246*E1246)-H1246,"")) | J1246: =IF(F1246="Full Cash", G1246, IF(F1246="Full Credit", I1246, IF(F1246="Partly Payment", H1246+I1246, ""))) | K1246: =IFERROR((E1246 - VLOOKUP(C1246, 'Stock Entry'!B:E, 4, FALSE)) * D1246, "")
I1247: =IF(F1247="Full Credit",D1247*E1247,IF(F1247="Partly Payment",(D1247*E1247)-H1247,"")) | J1247: =IF(F1247="Full Cash", G1247, IF(F1247="Full Credit", I1247, IF(F1247="Partly Payment", H1247+I1247, ""))) | K1247: =IFERROR((E1247 - VLOOKUP(C1247, 'Stock Entry'!B:E, 4, FALSE)) * D1247, "")

Sheet Stock Entry
A1: Date Added | B1: Product Name | C1: Description | D1: Quantity | E1: Buying Price | F1: Total
A2: 45597 | B2: NAMANVE | D2: 50 | E2: 102000 | F2: =IF((D2*E2)=0, "", D2*E2) -> 5100000
A3: 45638 | B3: MUYINDI | D3: 50 | E3: 112000 | F3: =IF((D3*E3)=0, "", D3*E3) -> 5600000
F4: =IF((D4*E4)=0, "", D4*E4)
F5: =IF((D5*E5)=0, "", D5*E5)
F6: =IF((D6*E6)=0, "", D6*E6)
F7: =IF((D7*E7)=0, "", D7*E7)
F8: =IF((D8*E8)=0, "", D8*E8)
F9: =IF((D9*E9)=0, "", D9*E9)
F10: =IF((D10*E10)=0, "", D10*E10)
F11: =IF((D11*E11)=0, "", D11*E11)
F12: =IF((D12*E12)=0, "", D12*E12)
F13: =IF((D13*E13)=0, "", D13*E13)
F14: =IF((D14*E14)=0, "", D14*E14)
F15: =IF((D15*E15)=0, "", D15*E15)
... F1210: =IF((D1210*E1210)=0, "", D1210*E1210)

Sheet Stock Remaining
A1: Product Name | B1: Quantity Stocked | C1: Quantity Sold | D1: Quantity Left | E1: Price | F1: Total Value
A2: {=IFERROR(INDEX('Stock Entry'!$B:$B, MATCH(0, COUNTIF($A$1:A1, 'Stock Entry'!$B:$B)+IF('Stock Entry'!$B:$B="",1,0), 0)), "")} -> NAMANVE | B2: =SUMIF('Stock Entry'!B:B, A2, 'Stock Entry'!D:D) -> 50 | C2: =SUMIF('Daily Sales'!C:C, A2, 'Daily Sales'!D:D) -> 5 | D2: =B2 - C2 -> 45 | E2: =VLOOKUP(A2, 'Stock Entry'!B:E, 4, FALSE) -> 102000 | F2: =D2 * E2 -> 4590000
A3: {=IFERROR(INDEX('Stock Entry'!$B:$B, MATCH(0, COUNTIF($A$1:A2, 'Stock Entry'!$B:$B)+IF('Stock Entry'!$B:$B="",1,0), 0)), "")} -> MUYINDI | B3: =SUMIF('Stock Entry'!B:B, A3, 'Stock Entry'!D:D) -> 50 | C3: =SUMIF('Daily Sales'!C:C, A3, 'Daily Sales'!D:D) -> 10 | D3: =B3 - C3 -> 40 | E3: =VLOOKUP(A3, 'Stock Entry'!B:E, 4, FALSE) -> 112000 | F3: =D3 * E3 -> 4480000
A4: {=IFERROR(INDEX('Stock Entry'!$B:$B, MATCH(0, COUNTIF($A$1:A3, 'Stock Entry'!$B:$B)+IF('Stock Entry'!$B:$B="",1,0), 0)), "")} | B4: =SUMIF('Stock Entry'!B:B, A4, 'Stock Entry'!D:D) -> 0 | C4: =SUMIF('Daily Sales'!C:C, A4, 'Daily Sales'!D:D) -> 0 | D4: =B4 - C4 -> 0 | E4: =VLOOKUP(A4, 'Stock Entry'!B:E, 4, FALSE) -> #N/A | F4: =D4 * E4 -> #N/A
A5: {=IFERROR(INDEX('Stock Entry'!$B:$B, MATCH(0, COUNTIF($A$1:A4, 'Stock Entry'!$B:$B)+IF('Stock Entry'!$B:$B="",1,0), 0)), "")} | B5: =SUMIF('Stock Entry'!B:B, A5, 'Stock Entry'!D:D) -> 0 | C5: =SUMIF('Daily Sales'!C:C, A5, 'Daily Sales'!D:D) -> 0 | D5: =B5 - C5 -> 0 | E5: =VLOOKUP(A5, 'Stock Entry'!B:E, 4, FALSE) -> #N/A | F5: =D5 * E5 -> #N/A
A6: {=IFERROR(INDEX('Stock Entry'!$B:$B, MATCH(0, COUNTIF($A$1:A5, 'Stock Entry'!$B:$B)+IF('Stock Entry'!$B:$B="",1,0), 0)), "")} | B6: =SUMIF('Stock Entry'!B:B, A6, 'Stock Entry'!D:D) -> 0 | C6: =SUMIF('Daily Sales'!C:C, A6, 'Daily Sales'!D:D) -> 0 | D6: =B6 - C6 -> 0 | E6: =VLOOKUP(A6, 'Stock Entry'!B:E, 4, FALSE) -> #N/A | F6: =D6 * E6 -> #N/A
A7: {=IFERROR(INDEX('Stock Entry'!$B:$B, MATCH(0, COUNTIF($A$1:A6, 'Stock Entry'!$B:$B)+IF('Stock Entry'!$B:$B="",1,0), 0)), "")} | B7: =SUMIF('Stock Entry'!B:B, A7, 'Stock Entry'!D:D) -> 0 | C7: =SUMIF('Daily Sales'!C:C, A7, 'Daily Sales'!D:D) -> 0 | D7: =B7 - C7 -> 0 | E7: =VLOOKUP(A7, 'Stock Entry'!B:E, 4, FALSE) -> #N/A | F7: =D7 * E7 -> #N/A
A8: {=IFERROR(INDEX('Stock Entry'!$B:$B, MATCH(0, COUNTIF($A$1:A7, 'Stock Entry'!$B:$B)+IF('Stock Entry'!$B:$B="",1,0), 0)), "")} | B8: =SUMIF('Stock Entry'!B:B, A8, 'Stock Entry'!D:D) -> 0 | C8: =SUMIF('Daily Sales'!C:C, A8, 'Daily Sales'!D:D) -> 0 | D8: =B8 - C8 -> 0 | E8: =VLOOKUP(A8, 'Stock Entry'!B:E, 4, FALSE) -> #N/A | F8: =D8 * E8 -> #N/A
A9: {=IFERROR(INDEX('Stock Entry'!$B:$B, MATCH(0, COUNTIF($A$1:A8, 'Stock Entry'!$B:$B)+IF('Stock Entry'!$B:$B="",1,0), 0)), "")} | B9: =SUMIF('Stock Entry'!B:B, A9, 'Stock Entry'!D:D) -> 0 | C9: =SUMIF('Daily Sales'!C:C, A9, 'Daily Sales'!D:D) -> 0 | D9: =B9 - C9 -> 0 | E9: =VLOOKUP(A9, 'Stock Entry'!B:E, 4, FALSE) -> #N/A | F9: =D9 * E9 -> #N/A
A10: {=IFERROR(INDEX('Stock Entry'!$B:$B, MATCH(0, COUNTIF($A$1:A9, 'Stock Entry'!$B:$B)+IF('Stock Entry'!$B:$B="",1,0), 0)), "")} | B10: =SUMIF('Stock Entry'!B:B, A10, 'Stock Entry'!D:D) -> 0 | C10: =SUMIF('Daily Sales'!C:C, A10, 'Daily Sales'!D:D) -> 0 | D10: =B10 - C10 -> 0 | E10: =VLOOKUP(A10, 'Stock Entry'!B:E, 4, FALSE) -> #N/A | F10: =D10 * E10 -> #N/A

Sheet Cumulative Performance
A1: Product Name | B1: Total Quantity Stocked | C1: Total Stocking Amount | D1: Total Quantity Sold | E1: Stock Amount Sold | F1: Total Amount of Sales | G1: Total Profits
A2: MUYINDI | B2: =IF(A2="", "", SUMIF('Stock Entry'!B:B, A2, 'Stock Entry'!D:D)) -> 50 | C2: =IF(A2="", "", SUMIF('Stock Entry'!B:B, A2, 'Stock Entry'!F:F)) -> 5600000 | D2: =IF(A2="", "", VLOOKUP(A2, 'Stock Remaining'!A:D, 3, FALSE)) -> 10 | E2: =IF(A2="", "", VLOOKUP(A2, 'Stock Entry'!B:E, 4, FALSE) * D2) -> 1120000 | F2: =IF(A2="", "", SUMIF('Daily Sales'!C:C, A2, 'Daily Sales'!J:J)) -> 1400000 | G2: =F2-E2 -> 280000
